{
  "CacheSourceKey": "8fqj91",
  "CachePdfKey": "8fqj91/8fqj91-1l5d4zc.pdf",
  "CacheXpzKey": "8fqj91/8fqj91-1317hvf.xpz",
  "CacheInfoKey": "8fqj91/8fqj91-1317hvf.json",
  "CacheCopyKey": null,
  "Document": "file-20210522130705329-detuluanmontoan.jpg",
  "DocumentHandlerType": null,
  "DocumentHandlerParameters": null,
  "DocumentLocation": "E:\\DoAn\\HeThongSoLienLac\\WEBSoLienLacDienTu\\WEBSoLienLacDienTu\\UploadedFiles",
  "DocumentFileName": "file-20210522130705329-detuluanmontoan.jpg",
  "InputOptions": {
    "Format": "Jpg",
    "Password": null
  },
  "PdfOutputOptions": {
    "Watermarks": [],
    "FastWebViewEnabled": false,
    "Password": null,
    "Attachments": [],
    "Format": "Pdf"
  },
  "XpzOutputOptions": {
    "Password": "8fqj91",
    "HighQualityEnabled": false,
    "Format": "Xpz"
  },
  "Attachments": []
}